{
  "generated_at": "2026-05-27T10:35:00.661Z",
  "draft": "backlink-url/auth-triage-pricing/pricing-review-decision-draft.csv",
  "batch_id": "auth-triage-freemium",
  "offset": 0,
  "limit": "20",
  "filters": {
    "suggested_decision": [
      "mark_freemium"
    ],
    "confidence": [],
    "include_reviewed": false
  },
  "constraints": {
    "read_only": true,
    "no_network": true,
    "no_registry_writes": true,
    "no_login": true,
    "no_submission": true,
    "no_mode_promotion": true,
    "review_decision_left_as_source": true
  },
  "total_draft_rows": 44,
  "matching_rows": 8,
  "remaining_after_batch": 0,
  "rows": [
    {
      "batch_id": "auth-triage-freemium",
      "batch_order": "1",
      "queue_order": "6",
      "target_id": "ashlist-com",
      "name": "https://ashlist.com",
      "domain": "ashlist.com",
      "mode": "assisted",
      "submit_url": "https://ashlist.com/",
      "current_pricing": "unknown",
      "suggested_pricing": "freemium",
      "suggested_review_decision": "mark_freemium",
      "suggestion_confidence": "medium",
      "review_decision": "",
      "reviewed_pricing": "",
      "reviewer": "",
      "reviewed_at": "",
      "review_notes": "",
      "evidence_url": "https://ashlist.com/",
      "evidence_matched": "yes",
      "http_status": "200",
      "fetch_ok": "yes",
      "payment_signal": "yes",
      "free_signal": "no",
      "freemium_signal": "yes",
      "captcha_signal": "no",
      "cloudflare_signal": "no",
      "suggestion_basis": "auth/login signal found; payment or paid-listing signal found; free plus premium/sponsored signal found; submit surface signal found; pricing/plan link or text found",
      "automation_policy": "pricing_decision_draft_no_registry_write_no_submission"
    },
    {
      "batch_id": "auth-triage-freemium",
      "batch_order": "2",
      "queue_order": "12",
      "target_id": "offpagesavvy",
      "name": "Offpagesavvy",
      "domain": "offpagesavvy.com",
      "mode": "assisted",
      "submit_url": "https://www.offpagesavvy.com/submit-your-site",
      "current_pricing": "unknown",
      "suggested_pricing": "freemium",
      "suggested_review_decision": "mark_freemium",
      "suggestion_confidence": "medium",
      "review_decision": "",
      "reviewed_pricing": "",
      "reviewer": "",
      "reviewed_at": "",
      "review_notes": "",
      "evidence_url": "https://www.offpagesavvy.com/submit-your-site",
      "evidence_matched": "yes",
      "http_status": "200",
      "fetch_ok": "yes",
      "payment_signal": "no",
      "free_signal": "no",
      "freemium_signal": "yes",
      "captcha_signal": "no",
      "cloudflare_signal": "no",
      "suggestion_basis": "free plus premium/sponsored signal found; submit surface signal found; pricing/plan link or text found",
      "automation_policy": "pricing_decision_draft_no_registry_write_no_submission"
    },
    {
      "batch_id": "auth-triage-freemium",
      "batch_order": "3",
      "queue_order": "21",
      "target_id": "solvertools-com",
      "name": "🔗 访问我们的网站",
      "domain": "solvertools.com",
      "mode": "assisted",
      "submit_url": "https://solvertools.com/",
      "current_pricing": "unknown",
      "suggested_pricing": "freemium",
      "suggested_review_decision": "mark_freemium",
      "suggestion_confidence": "medium",
      "review_decision": "",
      "reviewed_pricing": "",
      "reviewer": "",
      "reviewed_at": "",
      "review_notes": "",
      "evidence_url": "https://solvertools.com/",
      "evidence_matched": "yes",
      "http_status": "200",
      "fetch_ok": "yes",
      "payment_signal": "yes",
      "free_signal": "no",
      "freemium_signal": "yes",
      "captcha_signal": "no",
      "cloudflare_signal": "no",
      "suggestion_basis": "auth/login signal found; payment or paid-listing signal found; free plus premium/sponsored signal found; submit surface signal found; pricing/plan link or text found",
      "automation_policy": "pricing_decision_draft_no_registry_write_no_submission"
    },
    {
      "batch_id": "auth-triage-freemium",
      "batch_order": "4",
      "queue_order": "26",
      "target_id": "thecoretools-com",
      "name": "https://thecoretools.com",
      "domain": "thecoretools.com",
      "mode": "assisted",
      "submit_url": "https://thecoretools.com/",
      "current_pricing": "unknown",
      "suggested_pricing": "freemium",
      "suggested_review_decision": "mark_freemium",
      "suggestion_confidence": "medium",
      "review_decision": "",
      "reviewed_pricing": "",
      "reviewer": "",
      "reviewed_at": "",
      "review_notes": "",
      "evidence_url": "https://thecoretools.com/",
      "evidence_matched": "yes",
      "http_status": "200",
      "fetch_ok": "yes",
      "payment_signal": "yes",
      "free_signal": "no",
      "freemium_signal": "yes",
      "captcha_signal": "no",
      "cloudflare_signal": "no",
      "suggestion_basis": "auth/login signal found; payment or paid-listing signal found; free plus premium/sponsored signal found; submit surface signal found; pricing/plan link or text found",
      "automation_policy": "pricing_decision_draft_no_registry_write_no_submission"
    },
    {
      "batch_id": "auth-triage-freemium",
      "batch_order": "5",
      "queue_order": "27",
      "target_id": "tinytoolhub-com",
      "name": "https://tinytoolhub.com",
      "domain": "tinytoolhub.com",
      "mode": "assisted",
      "submit_url": "https://tinytoolhub.com/",
      "current_pricing": "unknown",
      "suggested_pricing": "freemium",
      "suggested_review_decision": "mark_freemium",
      "suggestion_confidence": "medium",
      "review_decision": "",
      "reviewed_pricing": "",
      "reviewer": "",
      "reviewed_at": "",
      "review_notes": "",
      "evidence_url": "https://tinytoolhub.com/",
      "evidence_matched": "yes",
      "http_status": "200",
      "fetch_ok": "yes",
      "payment_signal": "yes",
      "free_signal": "no",
      "freemium_signal": "yes",
      "captcha_signal": "no",
      "cloudflare_signal": "no",
      "suggestion_basis": "auth/login signal found; payment or paid-listing signal found; free plus premium/sponsored signal found; submit surface signal found; pricing/plan link or text found",
      "automation_policy": "pricing_decision_draft_no_registry_write_no_submission"
    },
    {
      "batch_id": "auth-triage-freemium",
      "batch_order": "6",
      "queue_order": "28",
      "target_id": "toolcosmos-com",
      "name": "https://toolcosmos.com",
      "domain": "toolcosmos.com",
      "mode": "assisted",
      "submit_url": "https://toolcosmos.com/",
      "current_pricing": "unknown",
      "suggested_pricing": "freemium",
      "suggested_review_decision": "mark_freemium",
      "suggestion_confidence": "medium",
      "review_decision": "",
      "reviewed_pricing": "",
      "reviewer": "",
      "reviewed_at": "",
      "review_notes": "",
      "evidence_url": "https://toolcosmos.com/",
      "evidence_matched": "yes",
      "http_status": "200",
      "fetch_ok": "yes",
      "payment_signal": "yes",
      "free_signal": "no",
      "freemium_signal": "yes",
      "captcha_signal": "no",
      "cloudflare_signal": "no",
      "suggestion_basis": "auth/login signal found; payment or paid-listing signal found; free plus premium/sponsored signal found; submit surface signal found; pricing/plan link or text found",
      "automation_policy": "pricing_decision_draft_no_registry_write_no_submission"
    },
    {
      "batch_id": "auth-triage-freemium",
      "batch_order": "7",
      "queue_order": "35",
      "target_id": "trustiner-com",
      "name": "https://trustiner.com",
      "domain": "trustiner.com",
      "mode": "assisted",
      "submit_url": "https://trustiner.com/",
      "current_pricing": "unknown",
      "suggested_pricing": "freemium",
      "suggested_review_decision": "mark_freemium",
      "suggestion_confidence": "medium",
      "review_decision": "",
      "reviewed_pricing": "",
      "reviewer": "",
      "reviewed_at": "",
      "review_notes": "",
      "evidence_url": "https://trustiner.com/",
      "evidence_matched": "yes",
      "http_status": "200",
      "fetch_ok": "yes",
      "payment_signal": "yes",
      "free_signal": "no",
      "freemium_signal": "yes",
      "captcha_signal": "no",
      "cloudflare_signal": "no",
      "suggestion_basis": "auth/login signal found; payment or paid-listing signal found; free plus premium/sponsored signal found; submit surface signal found; pricing/plan link or text found",
      "automation_policy": "pricing_decision_draft_no_registry_write_no_submission"
    },
    {
      "batch_id": "auth-triage-freemium",
      "batch_order": "8",
      "queue_order": "39",
      "target_id": "broadwise-org",
      "name": "Broadwise.org",
      "domain": "broadwise.org",
      "mode": "assisted",
      "submit_url": "https://broadwise.org/t/how-to-promote-your-startup-on-broadwise-org/125",
      "current_pricing": "unknown",
      "suggested_pricing": "freemium",
      "suggested_review_decision": "mark_freemium",
      "suggestion_confidence": "low",
      "review_decision": "",
      "reviewed_pricing": "",
      "reviewer": "",
      "reviewed_at": "",
      "review_notes": "",
      "evidence_url": "https://broadwise.org/t/how-to-promote-your-startup-on-broadwise-org/125",
      "evidence_matched": "yes",
      "http_status": "200",
      "fetch_ok": "yes",
      "payment_signal": "no",
      "free_signal": "no",
      "freemium_signal": "yes",
      "captcha_signal": "no",
      "cloudflare_signal": "no",
      "suggestion_basis": "free plus premium/sponsored signal found; pricing/plan link or text found",
      "automation_policy": "pricing_decision_draft_no_registry_write_no_submission"
    }
  ],
  "summary": {
    "rows": 8,
    "matching_rows": 8,
    "rows_requiring_human_review": 8,
    "by_suggested_review_decision": {
      "mark_freemium": 8
    },
    "by_suggested_pricing": {
      "freemium": 8
    },
    "by_confidence": {
      "medium": 7,
      "low": 1
    }
  },
  "files": {
    "batch_csv": "backlink-url/auth-triage-pricing/decision-batches/auth-triage-freemium.csv",
    "batch_json": "backlink-url/auth-triage-pricing/decision-batches/auth-triage-freemium.json",
    "batch_md": "backlink-url/auth-triage-pricing/decision-batches/auth-triage-freemium.md"
  }
}
